ilwis/__init__.py
ilwis/_ilwisobjects.so
ilwis/libilwiscore.so
ilwis/libilwiscore.so.1
ilwis/libilwiscore.so.1.0
ilwis/libilwiscore.so.1.0.0
ilwis/extensions/baseoperations/libbaseoperations.so
ilwis/extensions/baseoperations/libbaseoperations.so.1
ilwis/extensions/baseoperations/libbaseoperations.so.1.0
ilwis/extensions/baseoperations/libbaseoperations.so.1.0.0
ilwis/extensions/featureoperations/libfeatureoperations.so
ilwis/extensions/featureoperations/libfeatureoperations.so.1
ilwis/extensions/featureoperations/libfeatureoperations.so.1.0
ilwis/extensions/featureoperations/libfeatureoperations.so.1.0.0
ilwis/extensions/gdalconnector/libgdalconnector.so
ilwis/extensions/gdalconnector/libgdalconnector.so.1
ilwis/extensions/gdalconnector/libgdalconnector.so.1.0
ilwis/extensions/gdalconnector/libgdalconnector.so.1.0.0
ilwis/extensions/gdalconnector/resources/GDALLogoBW.svg
ilwis/extensions/gdalconnector/resources/GDALLogoColor.svg
ilwis/extensions/gdalconnector/resources/GDALLogoGS.svg
ilwis/extensions/gdalconnector/resources/compdcs.csv
ilwis/extensions/gdalconnector/resources/coordinate_axis.csv
ilwis/extensions/gdalconnector/resources/cubewerx_extra.wkt
ilwis/extensions/gdalconnector/resources/datum_shift.csv
ilwis/extensions/gdalconnector/resources/default.rsc
ilwis/extensions/gdalconnector/resources/ecw_cs.wkt
ilwis/extensions/gdalconnector/resources/ellipsoid.csv
ilwis/extensions/gdalconnector/resources/epsg.wkt
ilwis/extensions/gdalconnector/resources/esri_StatePlane_extra.wkt
ilwis/extensions/gdalconnector/resources/esri_Wisconsin_extra.wkt
ilwis/extensions/gdalconnector/resources/esri_extra.wkt
ilwis/extensions/gdalconnector/resources/gcs.csv
ilwis/extensions/gdalconnector/resources/gcs.override.csv
ilwis/extensions/gdalconnector/resources/gdal_datum.csv
ilwis/extensions/gdalconnector/resources/gdalicon.png
ilwis/extensions/gdalconnector/resources/gdalvrt.xsd
ilwis/extensions/gdalconnector/resources/geoccs.csv
ilwis-1.0.20250927.dist-info/METADATA
ilwis-1.0.20250927.dist-info/WHEEL
ilwis-1.0.20250927.dist-info/top_level.txt
ilwis-1.0.20250927.dist-info/RECORD
